{
	"siteVersion": "1.178.0",
	"_meta": {
		"sources": [
			{
				"json": "ProjectCriticalBastards",
				"abbreviation": "PCB",
				"full": "Project Critical Bastards",
				"url": "",
				"authors": [
					"Fergulho"
				],
				"convertedBy": []
			}
		],
		"dateAdded": 1681508682,
		"dateLastModified": 1681508682
	},
	"monster": [
		{
			"name": "Pirate (Gunslinger) - PCB",
			"source": "ProjectCriticalBastards",
			"page": 201,
			"size": [
				"M"
			],
			"type": "humanoid",
			"alignment": [
				"A"
			],
			"ac": [
				{
					"ac": 18,
					"from": [
						"{@item studded leather armor|phb|studded leather}",
						"{@item shield|phb}"
					]
				}
			],
			"hp": {
				"formula": "13d8 + 26",
				"average": 55
			},
			"speed": {
				"walk": 30
			},
			"str": 13,
			"dex": 18,
			"con": 14,
			"int": 11,
			"wis": 13,
			"cha": 14,
			"save": {
				"dex": "+6",
				"con": "+4",
				"wis": "+3"
			},
			"skill": {
				"perception": "+3",
				"stealth": "+8"
			},
			"passive": 13,
			"cr": "4",
			"trait": [
				{
					"name": "Gunslinger",
					"entries": [
						"Being within 5 feet of a hostile creature or attacking at long range doesn't impose disadvantage on the Gunslinger ranged attack rolls with a pistol. In addition, the drow ignores half cover and three-quarters cover when making ranged attacks with a pistol."
					]
				},
				{
					"name": "Sea Legs",
					"entries": [
						"The deck wizard has advantage on ability checks and saving throws to resist being knocked {@condition prone}."
					]
				}
			],
			"action": [
				{
					"name": "Multiattack",
					"entries": [
						"The drow makes two shortsword attacks."
					]
				},
				{
					"name": "Shortsword",
					"entries": [
						"{@atk mw} {@hit 6} to hit, reach 5 ft., one target. {@h}7 ({@damage 1d6 + 4}) piercing damage."
					]
				},
				{
					"name": "Pistol",
					"entries": [
						"{@atk rw} {@hit 6} to hit, range 30/90 ft., one target. {@h}9 ({@damage 1d10 + 4}) piercing damage."
					]
				}
			],
			"traitTags": [
				"Fey Ancestry",
				"Sunlight Sensitivity"
			],
			"actionTags": [
				"Multiattack"
			],
			"damageTags": [
				"P"
			],
			"miscTags": [
				"MW",
				"RW"
			],
			"hasFluff": true,
			"hasFluffImages": true,
			"tokenUrl": "https://i.imgur.com/dvpQOqw.png",
			"fluff": {
				"entries": [
					{
						"type": "entries",
						"entries": [
							{
								"type": "entries",
								"entries": [
									{
										"type": "entries",
										"entries": [
											"Firearms aren't widely available in the North, but some members of Bregan D'aerthe are equipped with Lantanese pistols, bullets, and packets of smokepowder. These drow gunslingers are expert pistoleers, as skilled with their guns as the best archers are with their bows."
										]
									}
								]
							}
						]
					}
				],
				"images": [
					{
						"type": "image",
						"href": {
							"type": "external",
							"url": "https://i.pinimg.com/564x/1b/79/8a/1b798a88f59bf0befd4b8e5eb1fc61d3.jpg"
						}
					}
				]
			},
			"languages": [
				"Common"
			],
			"languageTags": [
				"C"
			]
		}
	]
}